mr4mp/__init__.py
mr4mp/mr4mp.py
mr4mp-2.7.1.dist-info/LICENSE
mr4mp-2.7.1.dist-info/METADATA
mr4mp-2.7.1.dist-info/WHEEL
mr4mp-2.7.1.dist-info/top_level.txt
mr4mp-2.7.1.dist-info/RECORD
